{
  "stamp": "20260716T102826Z",
  "mode": "until_raw>=50.0|hist_curriculum",
  "target_raw": 50.0,
  "history": [
    {
      "gen": 49,
      "best_raw": -1.0,
      "best_fitness": [
        -1,
        -1,
        -1.0,
        -1.0,
        -1.0,
        -1.0
      ],
      "mean_raw_elite": -1.0,
      "elapsed_s": 4.179197788238525,
      "champ_raw": 19.29550679320724
    },
    {
      "gen": 50,
      "best_raw": -1.0,
      "best_fitness": [
        -1,
        -1,
        -1.0,
        -1.0,
        -1.0,
        -1.0
      ],
      "mean_raw_elite": -1.0,
      "elapsed_s": 4.361098527908325,
      "champ_raw": 19.29550679320724
    },
    {
      "gen": 51,
      "best_raw": -1.0,
      "best_fitness": [
        -1,
        -1,
        -1.0,
        -1.0,
        -1.0,
        -1.0
      ],
      "mean_raw_elite": -1.0,
      "elapsed_s": 4.374908685684204,
      "champ_raw": 19.29550679320724
    },
    {
      "gen": 52,
      "best_raw": -1.0,
      "best_fitness": [
        -1,
        -1,
        -1.0,
        -1.0,
        -1.0,
        -1.0
      ],
      "mean_raw_elite": -1.0,
      "elapsed_s": 4.23686957359314,
      "champ_raw": 19.29550679320724
    },
    {
      "gen": 53,
      "best_raw": -1.0,
      "best_fitness": [
        -1,
        -1,
        -1.0,
        -1.0,
        -1.0,
        -1.0
      ],
      "mean_raw_elite": -1.0,
      "elapsed_s": 4.304700136184692,
      "champ_raw": 19.29550679320724
    },
    {
      "gen": 54,
      "best_raw": -1.0,
      "best_fitness": [
        -1,
        -1,
        -1.0,
        -1.0,
        -1.0,
        -1.0
      ],
      "mean_raw_elite": -1.0,
      "elapsed_s": 4.162023544311523,
      "champ_raw": 19.29550679320724
    },
    {
      "gen": 55,
      "best_raw": -1.0,
      "best_fitness": [
        -1,
        -1,
        -1.0,
        -1.0,
        -1.0,
        -1.0
      ],
      "mean_raw_elite": -1.0,
      "elapsed_s": 4.222865343093872,
      "champ_raw": 19.29550679320724
    },
    {
      "gen": 56,
      "best_raw": -1.0,
      "best_fitness": [
        -1,
        -1,
        -1.0,
        -1.0,
        -1.0,
        -1.0
      ],
      "mean_raw_elite": -1.0,
      "elapsed_s": 4.491211891174316,
      "champ_raw": 19.29550679320724
    },
    {
      "gen": 57,
      "best_raw": -1.0,
      "best_fitness": [
        -1,
        -1,
        -1.0,
        -1.0,
        -1.0,
        -1.0
      ],
      "mean_raw_elite": -1.0,
      "elapsed_s": 4.345704078674316,
      "champ_raw": 19.29550679320724
    },
    {
      "gen": 58,
      "best_raw": -1.0,
      "best_fitness": [
        -1,
        -1,
        -1.0,
        -1.0,
        -1.0,
        -1.0
      ],
      "mean_raw_elite": -1.0,
      "elapsed_s": 4.259080171585083,
      "champ_raw": 19.29550679320724
    },
    {
      "gen": 59,
      "best_raw": -1.0,
      "best_fitness": [
        -1,
        -1,
        -1.0,
        -1.0,
        -1.0,
        -1.0
      ],
      "mean_raw_elite": -1.0,
      "elapsed_s": 4.44887638092041,
      "champ_raw": 19.29550679320724
    },
    {
      "gen": 60,
      "best_raw": -1.0,
      "best_fitness": [
        -1,
        -1,
        -1.0,
        -1.0,
        -1.0,
        -1.0
      ],
      "mean_raw_elite": -1.0,
      "elapsed_s": 4.3501136302948,
      "champ_raw": 19.29550679320724
    },
    {
      "gen": 61,
      "best_raw": -1.0,
      "best_fitness": [
        -1,
        -1,
        -1.0,
        -1.0,
        -1.0,
        -1.0
      ],
      "mean_raw_elite": -1.0,
      "elapsed_s": 4.199708700180054,
      "champ_raw": 19.29550679320724
    },
    {
      "gen": 62,
      "best_raw": -1.0,
      "best_fitness": [
        -1,
        -1,
        -1.0,
        -1.0,
        -1.0,
        -1.0
      ],
      "mean_raw_elite": -1.0,
      "elapsed_s": 4.316693067550659,
      "champ_raw": 19.29550679320724
    },
    {
      "gen": 63,
      "best_raw": -1.0,
      "best_fitness": [
        -1,
        -1,
        -1.0,
        -1.0,
        -1.0,
        -1.0
      ],
      "mean_raw_elite": -1.0,
      "elapsed_s": 4.389248847961426,
      "champ_raw": 19.29550679320724
    },
    {
      "gen": 64,
      "best_raw": -1.0,
      "best_fitness": [
        -1,
        -1,
        -1.0,
        -1.0,
        -1.0,
        -1.0
      ],
      "mean_raw_elite": -1.0,
      "elapsed_s": 4.373987913131714,
      "champ_raw": 19.29550679320724
    },
    {
      "gen": 65,
      "best_raw": -1.0,
      "best_fitness": [
        -1,
        -1,
        -1.0,
        -1.0,
        -1.0,
        -1.0
      ],
      "mean_raw_elite": -1.0,
      "elapsed_s": 4.411187648773193,
      "champ_raw": 19.29550679320724
    },
    {
      "gen": 66,
      "best_raw": -1.0,
      "best_fitness": [
        -1,
        -1,
        -1.0,
        -1.0,
        -1.0,
        -1.0
      ],
      "mean_raw_elite": -1.0,
      "elapsed_s": 4.203812599182129,
      "champ_raw": 19.29550679320724
    },
    {
      "gen": 67,
      "best_raw": -1.0,
      "best_fitness": [
        -1,
        -1,
        -1.0,
        -1.0,
        -1.0,
        -1.0
      ],
      "mean_raw_elite": -1.0,
      "elapsed_s": 4.384392499923706,
      "champ_raw": 19.29550679320724
    },
    {
      "gen": 68,
      "best_raw": -1.0,
      "best_fitness": [
        -1,
        -1,
        -1.0,
        -1.0,
        -1.0,
        -1.0
      ],
      "mean_raw_elite": -1.0,
      "elapsed_s": 4.3952696323394775,
      "champ_raw": 19.29550679320724
    },
    {
      "gen": 69,
      "best_raw": -1.0,
      "best_fitness": [
        -1,
        -1,
        -1.0,
        -1.0,
        -1.0,
        -1.0
      ],
      "mean_raw_elite": -1.0,
      "elapsed_s": 4.347619295120239,
      "champ_raw": 19.29550679320724
    },
    {
      "gen": 70,
      "best_raw": -1.0,
      "best_fitness": [
        -1,
        -1,
        -1.0,
        -1.0,
        -1.0,
        -1.0
      ],
      "mean_raw_elite": -1.0,
      "elapsed_s": 4.21895432472229,
      "champ_raw": 19.29550679320724
    },
    {
      "gen": 71,
      "best_raw": -1.0,
      "best_fitness": [
        -1,
        -1,
        -1.0,
        -1.0,
        -1.0,
        -1.0
      ],
      "mean_raw_elite": -1.0,
      "elapsed_s": 4.270347595214844,
      "champ_raw": 19.29550679320724
    },
    {
      "gen": 72,
      "best_raw": -1.0,
      "best_fitness": [
        -1,
        -1,
        -1.0,
        -1.0,
        -1.0,
        -1.0
      ],
      "mean_raw_elite": -1.0,
      "elapsed_s": 4.42512845993042,
      "champ_raw": 19.29550679320724
    },
    {
      "gen": 73,
      "best_raw": -1.0,
      "best_fitness": [
        -1,
        -1,
        -1.0,
        -1.0,
        -1.0,
        -1.0
      ],
      "mean_raw_elite": -1.0,
      "elapsed_s": 4.350701570510864,
      "champ_raw": 19.29550679320724
    },
    {
      "gen": 74,
      "best_raw": -1.0,
      "best_fitness": [
        -1,
        -1,
        -1.0,
        -1.0,
        -1.0,
        -1.0
      ],
      "mean_raw_elite": -1.0,
      "elapsed_s": 4.248446464538574,
      "champ_raw": 19.29550679320724
    },
    {
      "gen": 75,
      "best_raw": -1.0,
      "best_fitness": [
        -1,
        -1,
        -1.0,
        -1.0,
        -1.0,
        -1.0
      ],
      "mean_raw_elite": -1.0,
      "elapsed_s": 4.305656433105469,
      "champ_raw": 19.29550679320724
    },
    {
      "gen": 76,
      "best_raw": -1.0,
      "best_fitness": [
        -1,
        -1,
        -1.0,
        -1.0,
        -1.0,
        -1.0
      ],
      "mean_raw_elite": -1.0,
      "elapsed_s": 4.460824251174927,
      "champ_raw": 19.29550679320724
    },
    {
      "gen": 77,
      "best_raw": -1.0,
      "best_fitness": [
        -1,
        -1,
        -1.0,
        -1.0,
        -1.0,
        -1.0
      ],
      "mean_raw_elite": -1.0,
      "elapsed_s": 4.390697002410889,
      "champ_raw": 19.29550679320724
    },
    {
      "gen": 78,
      "best_raw": -1.0,
      "best_fitness": [
        -1,
        -1,
        -1.0,
        -1.0,
        -1.0,
        -1.0
      ],
      "mean_raw_elite": -1.0,
      "elapsed_s": 4.3393943309783936,
      "champ_raw": 19.29550679320724
    },
    {
      "gen": 79,
      "best_raw": -1.0,
      "best_fitness": [
        -1,
        -1,
        -1.0,
        -1.0,
        -1.0,
        -1.0
      ],
      "mean_raw_elite": -1.0,
      "elapsed_s": 4.42571759223938,
      "champ_raw": 19.29550679320724
    },
    {
      "gen": 80,
      "best_raw": -1.0,
      "best_fitness": [
        -1,
        -1,
        -1.0,
        -1.0,
        -1.0,
        -1.0
      ],
      "mean_raw_elite": -1.0,
      "elapsed_s": 4.198296070098877,
      "champ_raw": 19.29550679320724
    },
    {
      "gen": 81,
      "best_raw": -1.0,
      "best_fitness": [
        -1,
        -1,
        -1.0,
        -1.0,
        -1.0,
        -1.0
      ],
      "mean_raw_elite": -1.0,
      "elapsed_s": 4.264941453933716,
      "champ_raw": 19.29550679320724
    },
    {
      "gen": 82,
      "best_raw": -1.0,
      "best_fitness": [
        -1,
        -1,
        -1.0,
        -1.0,
        -1.0,
        -1.0
      ],
      "mean_raw_elite": -1.0,
      "elapsed_s": 4.2929768562316895,
      "champ_raw": 19.29550679320724
    },
    {
      "gen": 83,
      "best_raw": -1.0,
      "best_fitness": [
        -1,
        -1,
        -1.0,
        -1.0,
        -1.0,
        -1.0
      ],
      "mean_raw_elite": -1.0,
      "elapsed_s": 4.166529417037964,
      "champ_raw": 19.29550679320724
    },
    {
      "gen": 84,
      "best_raw": -1.0,
      "best_fitness": [
        -1,
        -1,
        -1.0,
        -1.0,
        -1.0,
        -1.0
      ],
      "mean_raw_elite": -1.0,
      "elapsed_s": 4.394406080245972,
      "champ_raw": 19.29550679320724
    },
    {
      "gen": 85,
      "best_raw": -1.0,
      "best_fitness": [
        -1,
        -1,
        -1.0,
        -1.0,
        -1.0,
        -1.0
      ],
      "mean_raw_elite": -1.0,
      "elapsed_s": 4.3972837924957275,
      "champ_raw": 19.29550679320724
    },
    {
      "gen": 86,
      "best_raw": -1.0,
      "best_fitness": [
        -1,
        -1,
        -1.0,
        -1.0,
        -1.0,
        -1.0
      ],
      "mean_raw_elite": -1.0,
      "elapsed_s": 4.344910621643066,
      "champ_raw": 19.29550679320724
    },
    {
      "gen": 87,
      "best_raw": -1.0,
      "best_fitness": [
        -1,
        -1,
        -1.0,
        -1.0,
        -1.0,
        -1.0
      ],
      "mean_raw_elite": -1.0,
      "elapsed_s": 4.3836798667907715,
      "champ_raw": 19.29550679320724
    },
    {
      "gen": 88,
      "best_raw": -1.0,
      "best_fitness": [
        -1,
        -1,
        -1.0,
        -1.0,
        -1.0,
        -1.0
      ],
      "mean_raw_elite": -1.0,
      "elapsed_s": 4.641277313232422,
      "champ_raw": 19.29550679320724
    },
    {
      "gen": 89,
      "best_raw": -1.0,
      "best_fitness": [
        -1,
        -1,
        -1.0,
        -1.0,
        -1.0,
        -1.0
      ],
      "mean_raw_elite": -1.0,
      "elapsed_s": 4.48201847076416,
      "champ_raw": 19.29550679320724
    },
    {
      "gen": 90,
      "best_raw": -1.0,
      "best_fitness": [
        -1,
        -1,
        -1.0,
        -1.0,
        -1.0,
        -1.0
      ],
      "mean_raw_elite": -1.0,
      "elapsed_s": 4.3004467487335205,
      "champ_raw": 19.29550679320724
    },
    {
      "gen": 91,
      "best_raw": -1.0,
      "best_fitness": [
        -1,
        -1,
        -1.0,
        -1.0,
        -1.0,
        -1.0
      ],
      "mean_raw_elite": -1.0,
      "elapsed_s": 4.28350043296814,
      "champ_raw": 19.29550679320724
    },
    {
      "gen": 92,
      "best_raw": -1.0,
      "best_fitness": [
        -1,
        -1,
        -1.0,
        -1.0,
        -1.0,
        -1.0
      ],
      "mean_raw_elite": -1.0,
      "elapsed_s": 4.3607025146484375,
      "champ_raw": 19.29550679320724
    },
    {
      "gen": 93,
      "best_raw": -1.0,
      "best_fitness": [
        -1,
        -1,
        -1.0,
        -1.0,
        -1.0,
        -1.0
      ],
      "mean_raw_elite": -1.0,
      "elapsed_s": 4.283748626708984,
      "champ_raw": 19.29550679320724
    },
    {
      "gen": 94,
      "best_raw": -1.0,
      "best_fitness": [
        -1,
        -1,
        -1.0,
        -1.0,
        -1.0,
        -1.0
      ],
      "mean_raw_elite": -1.0,
      "elapsed_s": 4.181217908859253,
      "champ_raw": 19.29550679320724
    },
    {
      "gen": 95,
      "best_raw": -1.0,
      "best_fitness": [
        -1,
        -1,
        -1.0,
        -1.0,
        -1.0,
        -1.0
      ],
      "mean_raw_elite": -1.0,
      "elapsed_s": 4.368384599685669,
      "champ_raw": 19.29550679320724
    },
    {
      "gen": 96,
      "best_raw": -1.0,
      "best_fitness": [
        -1,
        -1,
        -1.0,
        -1.0,
        -1.0,
        -1.0
      ],
      "mean_raw_elite": -1.0,
      "elapsed_s": 4.316420555114746,
      "champ_raw": 19.29550679320724
    },
    {
      "gen": 97,
      "best_raw": -1.0,
      "best_fitness": [
        -1,
        -1,
        -1.0,
        -1.0,
        -1.0,
        -1.0
      ],
      "mean_raw_elite": -1.0,
      "elapsed_s": 4.16842246055603,
      "champ_raw": 19.29550679320724
    },
    {
      "gen": 98,
      "best_raw": -1.0,
      "best_fitness": [
        -1,
        -1,
        -1.0,
        -1.0,
        -1.0,
        -1.0
      ],
      "mean_raw_elite": -1.0,
      "elapsed_s": 4.2644782066345215,
      "champ_raw": 19.29550679320724
    },
    {
      "gen": 99,
      "best_raw": -1.0,
      "best_fitness": [
        -1,
        -1,
        -1.0,
        -1.0,
        -1.0,
        -1.0
      ],
      "mean_raw_elite": -1.0,
      "elapsed_s": 4.277874946594238,
      "champ_raw": 19.29550679320724
    },
    {
      "gen": 100,
      "best_raw": -1.0,
      "best_fitness": [
        -1,
        -1,
        -1.0,
        -1.0,
        -1.0,
        -1.0
      ],
      "mean_raw_elite": -1.0,
      "elapsed_s": 4.3653724193573,
      "champ_raw": 19.29550679320724
    },
    {
      "gen": 101,
      "best_raw": -1.0,
      "best_fitness": [
        -1,
        -1,
        -1.0,
        -1.0,
        -1.0,
        -1.0
      ],
      "mean_raw_elite": -1.0,
      "elapsed_s": 4.263713836669922,
      "champ_raw": 19.29550679320724
    },
    {
      "gen": 102,
      "best_raw": -1.0,
      "best_fitness": [
        -1,
        -1,
        -1.0,
        -1.0,
        -1.0,
        -1.0
      ],
      "mean_raw_elite": -1.0,
      "elapsed_s": 4.476290464401245,
      "champ_raw": 19.29550679320724
    },
    {
      "gen": 103,
      "best_raw": -1.0,
      "best_fitness": [
        -1,
        -1,
        -1.0,
        -1.0,
        -1.0,
        -1.0
      ],
      "mean_raw_elite": -1.0,
      "elapsed_s": 4.18682336807251,
      "champ_raw": 19.29550679320724
    },
    {
      "gen": 104,
      "best_raw": -1.0,
      "best_fitness": [
        -1,
        -1,
        -1.0,
        -1.0,
        -1.0,
        -1.0
      ],
      "mean_raw_elite": -1.0,
      "elapsed_s": 4.420331716537476,
      "champ_raw": 19.29550679320724
    },
    {
      "gen": 105,
      "best_raw": -1.0,
      "best_fitness": [
        -1,
        -1,
        -1.0,
        -1.0,
        -1.0,
        -1.0
      ],
      "mean_raw_elite": -1.0,
      "elapsed_s": 4.234095573425293,
      "champ_raw": 19.29550679320724
    },
    {
      "gen": 106,
      "best_raw": -1.0,
      "best_fitness": [
        -1,
        -1,
        -1.0,
        -1.0,
        -1.0,
        -1.0
      ],
      "mean_raw_elite": -1.0,
      "elapsed_s": 4.362619876861572,
      "champ_raw": 19.29550679320724
    },
    {
      "gen": 107,
      "best_raw": -1.0,
      "best_fitness": [
        -1,
        -1,
        -1.0,
        -1.0,
        -1.0,
        -1.0
      ],
      "mean_raw_elite": -1.0,
      "elapsed_s": 4.238821983337402,
      "champ_raw": 19.29550679320724
    },
    {
      "gen": 108,
      "best_raw": -1.0,
      "best_fitness": [
        -1,
        -1,
        -1.0,
        -1.0,
        -1.0,
        -1.0
      ],
      "mean_raw_elite": -1.0,
      "elapsed_s": 4.231476068496704,
      "champ_raw": 19.29550679320724
    },
    {
      "gen": 109,
      "best_raw": -1.0,
      "best_fitness": [
        -1,
        -1,
        -1.0,
        -1.0,
        -1.0,
        -1.0
      ],
      "mean_raw_elite": -1.0,
      "elapsed_s": 4.266987323760986,
      "champ_raw": 19.29550679320724
    },
    {
      "gen": 110,
      "best_raw": -1.0,
      "best_fitness": [
        -1,
        -1,
        -1.0,
        -1.0,
        -1.0,
        -1.0
      ],
      "mean_raw_elite": -1.0,
      "elapsed_s": 4.220840930938721,
      "champ_raw": 19.29550679320724
    },
    {
      "gen": 111,
      "best_raw": -1.0,
      "best_fitness": [
        -1,
        -1,
        -1.0,
        -1.0,
        -1.0,
        -1.0
      ],
      "mean_raw_elite": -1.0,
      "elapsed_s": 4.4714672565460205,
      "champ_raw": 19.29550679320724
    },
    {
      "gen": 112,
      "best_raw": -1.0,
      "best_fitness": [
        -1,
        -1,
        -1.0,
        -1.0,
        -1.0,
        -1.0
      ],
      "mean_raw_elite": -1.0,
      "elapsed_s": 4.401890754699707,
      "champ_raw": 19.29550679320724
    },
    {
      "gen": 113,
      "best_raw": -1.0,
      "best_fitness": [
        -1,
        -1,
        -1.0,
        -1.0,
        -1.0,
        -1.0
      ],
      "mean_raw_elite": -1.0,
      "elapsed_s": 4.2223827838897705,
      "champ_raw": 19.29550679320724
    },
    {
      "gen": 114,
      "best_raw": -1.0,
      "best_fitness": [
        -1,
        -1,
        -1.0,
        -1.0,
        -1.0,
        -1.0
      ],
      "mean_raw_elite": -1.0,
      "elapsed_s": 4.278863191604614,
      "champ_raw": 19.29550679320724
    },
    {
      "gen": 115,
      "best_raw": -1.0,
      "best_fitness": [
        -1,
        -1,
        -1.0,
        -1.0,
        -1.0,
        -1.0
      ],
      "mean_raw_elite": -1.0,
      "elapsed_s": 4.312192916870117,
      "champ_raw": 19.29550679320724
    },
    {
      "gen": 116,
      "best_raw": -1.0,
      "best_fitness": [
        -1,
        -1,
        -1.0,
        -1.0,
        -1.0,
        -1.0
      ],
      "mean_raw_elite": -1.0,
      "elapsed_s": 4.208380937576294,
      "champ_raw": 19.29550679320724
    },
    {
      "gen": 117,
      "best_raw": -1.0,
      "best_fitness": [
        -1,
        -1,
        -1.0,
        -1.0,
        -1.0,
        -1.0
      ],
      "mean_raw_elite": -1.0,
      "elapsed_s": 4.292344331741333,
      "champ_raw": 19.29550679320724
    },
    {
      "gen": 118,
      "best_raw": -1.0,
      "best_fitness": [
        -1,
        -1,
        -1.0,
        -1.0,
        -1.0,
        -1.0
      ],
      "mean_raw_elite": -1.0,
      "elapsed_s": 4.33839750289917,
      "champ_raw": 19.29550679320724
    },
    {
      "gen": 119,
      "best_raw": -1.0,
      "best_fitness": [
        -1,
        -1,
        -1.0,
        -1.0,
        -1.0,
        -1.0
      ],
      "mean_raw_elite": -1.0,
      "elapsed_s": 4.312546491622925,
      "champ_raw": 19.29550679320724
    },
    {
      "gen": 120,
      "best_raw": -1.0,
      "best_fitness": [
        -1,
        -1,
        -1.0,
        -1.0,
        -1.0,
        -1.0
      ],
      "mean_raw_elite": -1.0,
      "elapsed_s": 4.277857542037964,
      "champ_raw": 19.29550679320724
    },
    {
      "gen": 121,
      "best_raw": -1.0,
      "best_fitness": [
        -1,
        -1,
        -1.0,
        -1.0,
        -1.0,
        -1.0
      ],
      "mean_raw_elite": -1.0,
      "elapsed_s": 4.302852630615234,
      "champ_raw": 19.29550679320724
    },
    {
      "gen": 122,
      "best_raw": -1.0,
      "best_fitness": [
        -1,
        -1,
        -1.0,
        -1.0,
        -1.0,
        -1.0
      ],
      "mean_raw_elite": -1.0,
      "elapsed_s": 4.236976861953735,
      "champ_raw": 19.29550679320724
    },
    {
      "gen": 123,
      "best_raw": -1.0,
      "best_fitness": [
        -1,
        -1,
        -1.0,
        -1.0,
        -1.0,
        -1.0
      ],
      "mean_raw_elite": -1.0,
      "elapsed_s": 4.382150650024414,
      "champ_raw": 19.29550679320724
    },
    {
      "gen": 124,
      "best_raw": -1.0,
      "best_fitness": [
        -1,
        -1,
        -1.0,
        -1.0,
        -1.0,
        -1.0
      ],
      "mean_raw_elite": -1.0,
      "elapsed_s": 4.335333585739136,
      "champ_raw": 19.29550679320724
    },
    {
      "gen": 125,
      "best_raw": -1.0,
      "best_fitness": [
        -1,
        -1,
        -1.0,
        -1.0,
        -1.0,
        -1.0
      ],
      "mean_raw_elite": -1.0,
      "elapsed_s": 4.100533485412598,
      "champ_raw": 19.29550679320724
    },
    {
      "gen": 126,
      "best_raw": -1.0,
      "best_fitness": [
        -1,
        -1,
        -1.0,
        -1.0,
        -1.0,
        -1.0
      ],
      "mean_raw_elite": -1.0,
      "elapsed_s": 4.345731496810913,
      "champ_raw": 19.29550679320724
    },
    {
      "gen": 127,
      "best_raw": -1.0,
      "best_fitness": [
        -1,
        -1,
        -1.0,
        -1.0,
        -1.0,
        -1.0
      ],
      "mean_raw_elite": -1.0,
      "elapsed_s": 4.336104393005371,
      "champ_raw": 19.29550679320724
    },
    {
      "gen": 128,
      "best_raw": -1.0,
      "best_fitness": [
        -1,
        -1,
        -1.0,
        -1.0,
        -1.0,
        -1.0
      ],
      "mean_raw_elite": -1.0,
      "elapsed_s": 4.273930311203003,
      "champ_raw": 19.29550679320724
    },
    {
      "gen": 129,
      "best_raw": -1.0,
      "best_fitness": [
        -1,
        -1,
        -1.0,
        -1.0,
        -1.0,
        -1.0
      ],
      "mean_raw_elite": -1.0,
      "elapsed_s": 4.1753270626068115,
      "champ_raw": 19.29550679320724
    },
    {
      "gen": 130,
      "best_raw": -1.0,
      "best_fitness": [
        -1,
        -1,
        -1.0,
        -1.0,
        -1.0,
        -1.0
      ],
      "mean_raw_elite": -1.0,
      "elapsed_s": 4.361729621887207,
      "champ_raw": 19.29550679320724
    },
    {
      "gen": 131,
      "best_raw": -1.0,
      "best_fitness": [
        -1,
        -1,
        -1.0,
        -1.0,
        -1.0,
        -1.0
      ],
      "mean_raw_elite": -1.0,
      "elapsed_s": 4.543176889419556,
      "champ_raw": 19.29550679320724
    },
    {
      "gen": 132,
      "best_raw": -1.0,
      "best_fitness": [
        -1,
        -1,
        -1.0,
        -1.0,
        -1.0,
        -1.0
      ],
      "mean_raw_elite": -1.0,
      "elapsed_s": 4.7532267570495605,
      "champ_raw": 19.29550679320724
    },
    {
      "gen": 133,
      "best_raw": -1.0,
      "best_fitness": [
        -1,
        -1,
        -1.0,
        -1.0,
        -1.0,
        -1.0
      ],
      "mean_raw_elite": -1.0,
      "elapsed_s": 4.552471160888672,
      "champ_raw": 19.29550679320724
    },
    {
      "gen": 134,
      "best_raw": -1.0,
      "best_fitness": [
        -1,
        -1,
        -1.0,
        -1.0,
        -1.0,
        -1.0
      ],
      "mean_raw_elite": -1.0,
      "elapsed_s": 4.482624769210815,
      "champ_raw": 19.29550679320724
    },
    {
      "gen": 135,
      "best_raw": -1.0,
      "best_fitness": [
        -1,
        -1,
        -1.0,
        -1.0,
        -1.0,
        -1.0
      ],
      "mean_raw_elite": -1.0,
      "elapsed_s": 4.469702482223511,
      "champ_raw": 19.29550679320724
    },
    {
      "gen": 136,
      "best_raw": -1.0,
      "best_fitness": [
        -1,
        -1,
        -1.0,
        -1.0,
        -1.0,
        -1.0
      ],
      "mean_raw_elite": -1.0,
      "elapsed_s": 4.321631908416748,
      "champ_raw": 19.29550679320724
    },
    {
      "gen": 137,
      "best_raw": -1.0,
      "best_fitness": [
        -1,
        -1,
        -1.0,
        -1.0,
        -1.0,
        -1.0
      ],
      "mean_raw_elite": -1.0,
      "elapsed_s": 4.2736546993255615,
      "champ_raw": 19.29550679320724
    },
    {
      "gen": 138,
      "best_raw": -1.0,
      "best_fitness": [
        -1,
        -1,
        -1.0,
        -1.0,
        -1.0,
        -1.0
      ],
      "mean_raw_elite": -1.0,
      "elapsed_s": 4.298079013824463,
      "champ_raw": 19.29550679320724
    },
    {
      "gen": 139,
      "best_raw": -1.0,
      "best_fitness": [
        -1,
        -1,
        -1.0,
        -1.0,
        -1.0,
        -1.0
      ],
      "mean_raw_elite": -1.0,
      "elapsed_s": 4.428873777389526,
      "champ_raw": 19.29550679320724
    },
    {
      "gen": 140,
      "best_raw": -1.0,
      "best_fitness": [
        -1,
        -1,
        -1.0,
        -1.0,
        -1.0,
        -1.0
      ],
      "mean_raw_elite": -1.0,
      "elapsed_s": 4.361199378967285,
      "champ_raw": 19.29550679320724
    },
    {
      "gen": 141,
      "best_raw": -1.0,
      "best_fitness": [
        -1,
        -1,
        -1.0,
        -1.0,
        -1.0,
        -1.0
      ],
      "mean_raw_elite": -1.0,
      "elapsed_s": 4.4109461307525635,
      "champ_raw": 19.29550679320724
    },
    {
      "gen": 142,
      "best_raw": -1.0,
      "best_fitness": [
        -1,
        -1,
        -1.0,
        -1.0,
        -1.0,
        -1.0
      ],
      "mean_raw_elite": -1.0,
      "elapsed_s": 4.518279552459717,
      "champ_raw": 19.29550679320724
    },
    {
      "gen": 143,
      "best_raw": -1.0,
      "best_fitness": [
        -1,
        -1,
        -1.0,
        -1.0,
        -1.0,
        -1.0
      ],
      "mean_raw_elite": -1.0,
      "elapsed_s": 4.7291038036346436,
      "champ_raw": 19.29550679320724
    },
    {
      "gen": 144,
      "best_raw": -1.0,
      "best_fitness": [
        -1,
        -1,
        -1.0,
        -1.0,
        -1.0,
        -1.0
      ],
      "mean_raw_elite": -1.0,
      "elapsed_s": 4.453875541687012,
      "champ_raw": 19.29550679320724
    },
    {
      "gen": 145,
      "best_raw": -1.0,
      "best_fitness": [
        -1,
        -1,
        -1.0,
        -1.0,
        -1.0,
        -1.0
      ],
      "mean_raw_elite": -1.0,
      "elapsed_s": 4.310269594192505,
      "champ_raw": 19.29550679320724
    },
    {
      "gen": 146,
      "best_raw": -1.0,
      "best_fitness": [
        -1,
        -1,
        -1.0,
        -1.0,
        -1.0,
        -1.0
      ],
      "mean_raw_elite": -1.0,
      "elapsed_s": 4.373990058898926,
      "champ_raw": 19.29550679320724
    },
    {
      "gen": 147,
      "best_raw": -1.0,
      "best_fitness": [
        -1,
        -1,
        -1.0,
        -1.0,
        -1.0,
        -1.0
      ],
      "mean_raw_elite": -1.0,
      "elapsed_s": 4.232557773590088,
      "champ_raw": 19.29550679320724
    },
    {
      "gen": 148,
      "best_raw": -1.0,
      "best_fitness": [
        -1,
        -1,
        -1.0,
        -1.0,
        -1.0,
        -1.0
      ],
      "mean_raw_elite": -1.0,
      "elapsed_s": 4.304283857345581,
      "champ_raw": 19.29550679320724
    },
    {
      "gen": 149,
      "best_raw": -1.0,
      "best_fitness": [
        -1,
        -1,
        -1.0,
        -1.0,
        -1.0,
        -1.0
      ],
      "mean_raw_elite": -1.0,
      "elapsed_s": 4.2450270652771,
      "champ_raw": 19.29550679320724
    },
    {
      "gen": 150,
      "best_raw": -1.0,
      "best_fitness": [
        -1,
        -1,
        -1.0,
        -1.0,
        -1.0,
        -1.0
      ],
      "mean_raw_elite": -1.0,
      "elapsed_s": 4.390077590942383,
      "champ_raw": 19.29550679320724
    },
    {
      "gen": 151,
      "best_raw": -1.0,
      "best_fitness": [
        -1,
        -1,
        -1.0,
        -1.0,
        -1.0,
        -1.0
      ],
      "mean_raw_elite": -1.0,
      "elapsed_s": 4.416764974594116,
      "champ_raw": 19.29550679320724
    },
    {
      "gen": 152,
      "best_raw": -1.0,
      "best_fitness": [
        -1,
        -1,
        -1.0,
        -1.0,
        -1.0,
        -1.0
      ],
      "mean_raw_elite": -1.0,
      "elapsed_s": 4.346992492675781,
      "champ_raw": 19.29550679320724
    },
    {
      "gen": 153,
      "best_raw": -1.0,
      "best_fitness": [
        -1,
        -1,
        -1.0,
        -1.0,
        -1.0,
        -1.0
      ],
      "mean_raw_elite": -1.0,
      "elapsed_s": 4.315015554428101,
      "champ_raw": 19.29550679320724
    },
    {
      "gen": 154,
      "best_raw": -1.0,
      "best_fitness": [
        -1,
        -1,
        -1.0,
        -1.0,
        -1.0,
        -1.0
      ],
      "mean_raw_elite": -1.0,
      "elapsed_s": 4.334489107131958,
      "champ_raw": 19.29550679320724
    },
    {
      "gen": 155,
      "best_raw": -1.0,
      "best_fitness": [
        -1,
        -1,
        -1.0,
        -1.0,
        -1.0,
        -1.0
      ],
      "mean_raw_elite": -1.0,
      "elapsed_s": 4.348183870315552,
      "champ_raw": 19.29550679320724
    },
    {
      "gen": 156,
      "best_raw": -1.0,
      "best_fitness": [
        -1,
        -1,
        -1.0,
        -1.0,
        -1.0,
        -1.0
      ],
      "mean_raw_elite": -1.0,
      "elapsed_s": 4.33224630355835,
      "champ_raw": 19.29550679320724
    },
    {
      "gen": 157,
      "best_raw": -1.0,
      "best_fitness": [
        -1,
        -1,
        -1.0,
        -1.0,
        -1.0,
        -1.0
      ],
      "mean_raw_elite": -1.0,
      "elapsed_s": 4.319002389907837,
      "champ_raw": 19.29550679320724
    },
    {
      "gen": 158,
      "best_raw": -1.0,
      "best_fitness": [
        -1,
        -1,
        -1.0,
        -1.0,
        -1.0,
        -1.0
      ],
      "mean_raw_elite": -1.0,
      "elapsed_s": 4.385995864868164,
      "champ_raw": 19.29550679320724
    },
    {
      "gen": 159,
      "best_raw": -1.0,
      "best_fitness": [
        -1,
        -1,
        -1.0,
        -1.0,
        -1.0,
        -1.0
      ],
      "mean_raw_elite": -1.0,
      "elapsed_s": 4.201877593994141,
      "champ_raw": 19.29550679320724
    },
    {
      "gen": 160,
      "best_raw": -1.0,
      "best_fitness": [
        -1,
        -1,
        -1.0,
        -1.0,
        -1.0,
        -1.0
      ],
      "mean_raw_elite": -1.0,
      "elapsed_s": 4.2473297119140625,
      "champ_raw": 19.29550679320724
    },
    {
      "gen": 161,
      "best_raw": -1.0,
      "best_fitness": [
        -1,
        -1,
        -1.0,
        -1.0,
        -1.0,
        -1.0
      ],
      "mean_raw_elite": -1.0,
      "elapsed_s": 4.308474063873291,
      "champ_raw": 19.29550679320724
    },
    {
      "gen": 162,
      "best_raw": -1.0,
      "best_fitness": [
        -1,
        -1,
        -1.0,
        -1.0,
        -1.0,
        -1.0
      ],
      "mean_raw_elite": -1.0,
      "elapsed_s": 4.296773433685303,
      "champ_raw": 19.29550679320724
    },
    {
      "gen": 163,
      "best_raw": -1.0,
      "best_fitness": [
        -1,
        -1,
        -1.0,
        -1.0,
        -1.0,
        -1.0
      ],
      "mean_raw_elite": -1.0,
      "elapsed_s": 4.297317028045654,
      "champ_raw": 19.29550679320724
    },
    {
      "gen": 164,
      "best_raw": -1.0,
      "best_fitness": [
        -1,
        -1,
        -1.0,
        -1.0,
        -1.0,
        -1.0
      ],
      "mean_raw_elite": -1.0,
      "elapsed_s": 4.2221434116363525,
      "champ_raw": 19.29550679320724
    },
    {
      "gen": 165,
      "best_raw": -1.0,
      "best_fitness": [
        -1,
        -1,
        -1.0,
        -1.0,
        -1.0,
        -1.0
      ],
      "mean_raw_elite": -1.0,
      "elapsed_s": 4.287364482879639,
      "champ_raw": 19.29550679320724
    },
    {
      "gen": 166,
      "best_raw": -1.0,
      "best_fitness": [
        -1,
        -1,
        -1.0,
        -1.0,
        -1.0,
        -1.0
      ],
      "mean_raw_elite": -1.0,
      "elapsed_s": 4.243571043014526,
      "champ_raw": 19.29550679320724
    },
    {
      "gen": 167,
      "best_raw": -1.0,
      "best_fitness": [
        -1,
        -1,
        -1.0,
        -1.0,
        -1.0,
        -1.0
      ],
      "mean_raw_elite": -1.0,
      "elapsed_s": 4.447258472442627,
      "champ_raw": 19.29550679320724
    },
    {
      "gen": 168,
      "best_raw": -1.0,
      "best_fitness": [
        -1,
        -1,
        -1.0,
        -1.0,
        -1.0,
        -1.0
      ],
      "mean_raw_elite": -1.0,
      "elapsed_s": 4.27994441986084,
      "champ_raw": 19.29550679320724
    },
    {
      "gen": 169,
      "best_raw": -1.0,
      "best_fitness": [
        -1,
        -1,
        -1.0,
        -1.0,
        -1.0,
        -1.0
      ],
      "mean_raw_elite": -1.0,
      "elapsed_s": 4.311251401901245,
      "champ_raw": 19.29550679320724
    },
    {
      "gen": 170,
      "best_raw": -1.0,
      "best_fitness": [
        -1,
        -1,
        -1.0,
        -1.0,
        -1.0,
        -1.0
      ],
      "mean_raw_elite": -1.0,
      "elapsed_s": 4.305823087692261,
      "champ_raw": 19.29550679320724
    },
    {
      "gen": 171,
      "best_raw": -1.0,
      "best_fitness": [
        -1,
        -1,
        -1.0,
        -1.0,
        -1.0,
        -1.0
      ],
      "mean_raw_elite": -1.0,
      "elapsed_s": 4.328091144561768,
      "champ_raw": 19.29550679320724
    },
    {
      "gen": 172,
      "best_raw": -1.0,
      "best_fitness": [
        -1,
        -1,
        -1.0,
        -1.0,
        -1.0,
        -1.0
      ],
      "mean_raw_elite": -1.0,
      "elapsed_s": 4.3361663818359375,
      "champ_raw": 19.29550679320724
    },
    {
      "gen": 173,
      "best_raw": -1.0,
      "best_fitness": [
        -1,
        -1,
        -1.0,
        -1.0,
        -1.0,
        -1.0
      ],
      "mean_raw_elite": -1.0,
      "elapsed_s": 4.3715105056762695,
      "champ_raw": 19.29550679320724
    },
    {
      "gen": 174,
      "best_raw": -1.0,
      "best_fitness": [
        -1,
        -1,
        -1.0,
        -1.0,
        -1.0,
        -1.0
      ],
      "mean_raw_elite": -1.0,
      "elapsed_s": 4.24575662612915,
      "champ_raw": 19.29550679320724
    },
    {
      "gen": 175,
      "best_raw": -1.0,
      "best_fitness": [
        -1,
        -1,
        -1.0,
        -1.0,
        -1.0,
        -1.0
      ],
      "mean_raw_elite": -1.0,
      "elapsed_s": 4.32792067527771,
      "champ_raw": 19.29550679320724
    },
    {
      "gen": 176,
      "best_raw": -1.0,
      "best_fitness": [
        -1,
        -1,
        -1.0,
        -1.0,
        -1.0,
        -1.0
      ],
      "mean_raw_elite": -1.0,
      "elapsed_s": 4.243646621704102,
      "champ_raw": 19.29550679320724
    },
    {
      "gen": 177,
      "best_raw": -1.0,
      "best_fitness": [
        -1,
        -1,
        -1.0,
        -1.0,
        -1.0,
        -1.0
      ],
      "mean_raw_elite": -1.0,
      "elapsed_s": 4.270860910415649,
      "champ_raw": 19.29550679320724
    },
    {
      "gen": 178,
      "best_raw": -1.0,
      "best_fitness": [
        -1,
        -1,
        -1.0,
        -1.0,
        -1.0,
        -1.0
      ],
      "mean_raw_elite": -1.0,
      "elapsed_s": 4.490152835845947,
      "champ_raw": 19.29550679320724
    },
    {
      "gen": 179,
      "best_raw": -1.0,
      "best_fitness": [
        -1,
        -1,
        -1.0,
        -1.0,
        -1.0,
        -1.0
      ],
      "mean_raw_elite": -1.0,
      "elapsed_s": 4.342056512832642,
      "champ_raw": 19.29550679320724
    },
    {
      "gen": 180,
      "best_raw": -1.0,
      "best_fitness": [
        -1,
        -1,
        -1.0,
        -1.0,
        -1.0,
        -1.0
      ],
      "mean_raw_elite": -1.0,
      "elapsed_s": 4.469430446624756,
      "champ_raw": 19.29550679320724
    },
    {
      "gen": 181,
      "best_raw": -1.0,
      "best_fitness": [
        -1,
        -1,
        -1.0,
        -1.0,
        -1.0,
        -1.0
      ],
      "mean_raw_elite": -1.0,
      "elapsed_s": 4.207809925079346,
      "champ_raw": 19.29550679320724
    },
    {
      "gen": 182,
      "best_raw": -1.0,
      "best_fitness": [
        -1,
        -1,
        -1.0,
        -1.0,
        -1.0,
        -1.0
      ],
      "mean_raw_elite": -1.0,
      "elapsed_s": 4.426020860671997,
      "champ_raw": 19.29550679320724
    },
    {
      "gen": 183,
      "best_raw": -1.0,
      "best_fitness": [
        -1,
        -1,
        -1.0,
        -1.0,
        -1.0,
        -1.0
      ],
      "mean_raw_elite": -1.0,
      "elapsed_s": 4.205008029937744,
      "champ_raw": 19.29550679320724
    },
    {
      "gen": 184,
      "best_raw": -1.0,
      "best_fitness": [
        -1,
        -1,
        -1.0,
        -1.0,
        -1.0,
        -1.0
      ],
      "mean_raw_elite": -1.0,
      "elapsed_s": 4.270787715911865,
      "champ_raw": 19.29550679320724
    },
    {
      "gen": 185,
      "best_raw": -1.0,
      "best_fitness": [
        -1,
        -1,
        -1.0,
        -1.0,
        -1.0,
        -1.0
      ],
      "mean_raw_elite": -1.0,
      "elapsed_s": 4.37906813621521,
      "champ_raw": 19.29550679320724
    },
    {
      "gen": 186,
      "best_raw": -1.0,
      "best_fitness": [
        -1,
        -1,
        -1.0,
        -1.0,
        -1.0,
        -1.0
      ],
      "mean_raw_elite": -1.0,
      "elapsed_s": 4.300933361053467,
      "champ_raw": 19.29550679320724
    },
    {
      "gen": 187,
      "best_raw": -1.0,
      "best_fitness": [
        -1,
        -1,
        -1.0,
        -1.0,
        -1.0,
        -1.0
      ],
      "mean_raw_elite": -1.0,
      "elapsed_s": 4.316576957702637,
      "champ_raw": 19.29550679320724
    },
    {
      "gen": 188,
      "best_raw": -1.0,
      "best_fitness": [
        -1,
        -1,
        -1.0,
        -1.0,
        -1.0,
        -1.0
      ],
      "mean_raw_elite": -1.0,
      "elapsed_s": 4.186874151229858,
      "champ_raw": 19.29550679320724
    },
    {
      "gen": 189,
      "best_raw": -1.0,
      "best_fitness": [
        -1,
        -1,
        -1.0,
        -1.0,
        -1.0,
        -1.0
      ],
      "mean_raw_elite": -1.0,
      "elapsed_s": 4.231975078582764,
      "champ_raw": 19.29550679320724
    },
    {
      "gen": 190,
      "best_raw": -1.0,
      "best_fitness": [
        -1,
        -1,
        -1.0,
        -1.0,
        -1.0,
        -1.0
      ],
      "mean_raw_elite": -1.0,
      "elapsed_s": 4.378829002380371,
      "champ_raw": 19.29550679320724
    },
    {
      "gen": 191,
      "best_raw": -1.0,
      "best_fitness": [
        -1,
        -1,
        -1.0,
        -1.0,
        -1.0,
        -1.0
      ],
      "mean_raw_elite": -1.0,
      "elapsed_s": 4.2255823612213135,
      "champ_raw": 19.29550679320724
    },
    {
      "gen": 192,
      "best_raw": -1.0,
      "best_fitness": [
        -1,
        -1,
        -1.0,
        -1.0,
        -1.0,
        -1.0
      ],
      "mean_raw_elite": -1.0,
      "elapsed_s": 4.411532878875732,
      "champ_raw": 19.29550679320724
    },
    {
      "gen": 193,
      "best_raw": -1.0,
      "best_fitness": [
        -1,
        -1,
        -1.0,
        -1.0,
        -1.0,
        -1.0
      ],
      "mean_raw_elite": -1.0,
      "elapsed_s": 4.364588975906372,
      "champ_raw": 19.29550679320724
    },
    {
      "gen": 194,
      "best_raw": -1.0,
      "best_fitness": [
        -1,
        -1,
        -1.0,
        -1.0,
        -1.0,
        -1.0
      ],
      "mean_raw_elite": -1.0,
      "elapsed_s": 4.234428644180298,
      "champ_raw": 19.29550679320724
    },
    {
      "gen": 195,
      "best_raw": -1.0,
      "best_fitness": [
        -1,
        -1,
        -1.0,
        -1.0,
        -1.0,
        -1.0
      ],
      "mean_raw_elite": -1.0,
      "elapsed_s": 4.210485219955444,
      "champ_raw": 19.29550679320724
    },
    {
      "gen": 196,
      "best_raw": -1.0,
      "best_fitness": [
        -1,
        -1,
        -1.0,
        -1.0,
        -1.0,
        -1.0
      ],
      "mean_raw_elite": -1.0,
      "elapsed_s": 4.1423728466033936,
      "champ_raw": 19.29550679320724
    },
    {
      "gen": 197,
      "best_raw": -1.0,
      "best_fitness": [
        -1,
        -1,
        -1.0,
        -1.0,
        -1.0,
        -1.0
      ],
      "mean_raw_elite": -1.0,
      "elapsed_s": 4.336506605148315,
      "champ_raw": 19.29550679320724
    },
    {
      "gen": 198,
      "best_raw": -1.0,
      "best_fitness": [
        -1,
        -1,
        -1.0,
        -1.0,
        -1.0,
        -1.0
      ],
      "mean_raw_elite": -1.0,
      "elapsed_s": 4.244425535202026,
      "champ_raw": 19.29550679320724
    },
    {
      "gen": 199,
      "best_raw": -1.0,
      "best_fitness": [
        -1,
        -1,
        -1.0,
        -1.0,
        -1.0,
        -1.0
      ],
      "mean_raw_elite": -1.0,
      "elapsed_s": 4.3415367603302,
      "champ_raw": 19.29550679320724
    },
    {
      "gen": 200,
      "best_raw": -1.0,
      "best_fitness": [
        -1,
        -1,
        -1.0,
        -1.0,
        -1.0,
        -1.0
      ],
      "mean_raw_elite": -1.0,
      "elapsed_s": 4.30364465713501,
      "champ_raw": 19.29550679320724
    },
    {
      "gen": 201,
      "best_raw": -1.0,
      "best_fitness": [
        -1,
        -1,
        -1.0,
        -1.0,
        -1.0,
        -1.0
      ],
      "mean_raw_elite": -1.0,
      "elapsed_s": 4.40631365776062,
      "champ_raw": 19.29550679320724
    },
    {
      "gen": 202,
      "best_raw": -1.0,
      "best_fitness": [
        -1,
        -1,
        -1.0,
        -1.0,
        -1.0,
        -1.0
      ],
      "mean_raw_elite": -1.0,
      "elapsed_s": 4.348231792449951,
      "champ_raw": 19.29550679320724
    },
    {
      "gen": 203,
      "best_raw": -1.0,
      "best_fitness": [
        -1,
        -1,
        -1.0,
        -1.0,
        -1.0,
        -1.0
      ],
      "mean_raw_elite": -1.0,
      "elapsed_s": 4.309368371963501,
      "champ_raw": 19.29550679320724
    },
    {
      "gen": 204,
      "best_raw": -1.0,
      "best_fitness": [
        -1,
        -1,
        -1.0,
        -1.0,
        -1.0,
        -1.0
      ],
      "mean_raw_elite": -1.0,
      "elapsed_s": 4.454944372177124,
      "champ_raw": 19.29550679320724
    },
    {
      "gen": 205,
      "best_raw": -1.0,
      "best_fitness": [
        -1,
        -1,
        -1.0,
        -1.0,
        -1.0,
        -1.0
      ],
      "mean_raw_elite": -1.0,
      "elapsed_s": 4.43572735786438,
      "champ_raw": 19.29550679320724
    },
    {
      "gen": 206,
      "best_raw": -1.0,
      "best_fitness": [
        -1,
        -1,
        -1.0,
        -1.0,
        -1.0,
        -1.0
      ],
      "mean_raw_elite": -1.0,
      "elapsed_s": 4.233826398849487,
      "champ_raw": 19.29550679320724
    },
    {
      "gen": 207,
      "best_raw": -1.0,
      "best_fitness": [
        -1,
        -1,
        -1.0,
        -1.0,
        -1.0,
        -1.0
      ],
      "mean_raw_elite": -1.0,
      "elapsed_s": 4.258873224258423,
      "champ_raw": 19.29550679320724
    },
    {
      "gen": 208,
      "best_raw": -1.0,
      "best_fitness": [
        -1,
        -1,
        -1.0,
        -1.0,
        -1.0,
        -1.0
      ],
      "mean_raw_elite": -1.0,
      "elapsed_s": 4.357596158981323,
      "champ_raw": 19.29550679320724
    },
    {
      "gen": 209,
      "best_raw": -1.0,
      "best_fitness": [
        -1,
        -1,
        -1.0,
        -1.0,
        -1.0,
        -1.0
      ],
      "mean_raw_elite": -1.0,
      "elapsed_s": 4.246554374694824,
      "champ_raw": 19.29550679320724
    },
    {
      "gen": 210,
      "best_raw": -1.0,
      "best_fitness": [
        -1,
        -1,
        -1.0,
        -1.0,
        -1.0,
        -1.0
      ],
      "mean_raw_elite": -1.0,
      "elapsed_s": 4.107237339019775,
      "champ_raw": 19.29550679320724
    },
    {
      "gen": 211,
      "best_raw": -1.0,
      "best_fitness": [
        -1,
        -1,
        -1.0,
        -1.0,
        -1.0,
        -1.0
      ],
      "mean_raw_elite": -1.0,
      "elapsed_s": 4.166520595550537,
      "champ_raw": 19.29550679320724
    },
    {
      "gen": 212,
      "best_raw": -1.0,
      "best_fitness": [
        -1,
        -1,
        -1.0,
        -1.0,
        -1.0,
        -1.0
      ],
      "mean_raw_elite": -1.0,
      "elapsed_s": 4.319134712219238,
      "champ_raw": 19.29550679320724
    },
    {
      "gen": 213,
      "best_raw": -1.0,
      "best_fitness": [
        -1,
        -1,
        -1.0,
        -1.0,
        -1.0,
        -1.0
      ],
      "mean_raw_elite": -1.0,
      "elapsed_s": 4.237435340881348,
      "champ_raw": 19.29550679320724
    },
    {
      "gen": 214,
      "best_raw": -1.0,
      "best_fitness": [
        -1,
        -1,
        -1.0,
        -1.0,
        -1.0,
        -1.0
      ],
      "mean_raw_elite": -1.0,
      "elapsed_s": 4.325998067855835,
      "champ_raw": 19.29550679320724
    },
    {
      "gen": 215,
      "best_raw": -1.0,
      "best_fitness": [
        -1,
        -1,
        -1.0,
        -1.0,
        -1.0,
        -1.0
      ],
      "mean_raw_elite": -1.0,
      "elapsed_s": 4.2830283641815186,
      "champ_raw": 19.29550679320724
    },
    {
      "gen": 216,
      "best_raw": -1.0,
      "best_fitness": [
        -1,
        -1,
        -1.0,
        -1.0,
        -1.0,
        -1.0
      ],
      "mean_raw_elite": -1.0,
      "elapsed_s": 4.426904678344727,
      "champ_raw": 19.29550679320724
    },
    {
      "gen": 217,
      "best_raw": -1.0,
      "best_fitness": [
        -1,
        -1,
        -1.0,
        -1.0,
        -1.0,
        -1.0
      ],
      "mean_raw_elite": -1.0,
      "elapsed_s": 4.502442359924316,
      "champ_raw": 19.29550679320724
    },
    {
      "gen": 218,
      "best_raw": -1.0,
      "best_fitness": [
        -1,
        -1,
        -1.0,
        -1.0,
        -1.0,
        -1.0
      ],
      "mean_raw_elite": -1.0,
      "elapsed_s": 4.3897693157196045,
      "champ_raw": 19.29550679320724
    },
    {
      "gen": 219,
      "best_raw": -1.0,
      "best_fitness": [
        -1,
        -1,
        -1.0,
        -1.0,
        -1.0,
        -1.0
      ],
      "mean_raw_elite": -1.0,
      "elapsed_s": 4.237326145172119,
      "champ_raw": 19.29550679320724
    },
    {
      "gen": 220,
      "best_raw": -1.0,
      "best_fitness": [
        -1,
        -1,
        -1.0,
        -1.0,
        -1.0,
        -1.0
      ],
      "mean_raw_elite": -1.0,
      "elapsed_s": 4.249495029449463,
      "champ_raw": 19.29550679320724
    },
    {
      "gen": 221,
      "best_raw": -1.0,
      "best_fitness": [
        -1,
        -1,
        -1.0,
        -1.0,
        -1.0,
        -1.0
      ],
      "mean_raw_elite": -1.0,
      "elapsed_s": 4.173475980758667,
      "champ_raw": 19.29550679320724
    },
    {
      "gen": 222,
      "best_raw": -1.0,
      "best_fitness": [
        -1,
        -1,
        -1.0,
        -1.0,
        -1.0,
        -1.0
      ],
      "mean_raw_elite": -1.0,
      "elapsed_s": 4.303629159927368,
      "champ_raw": 19.29550679320724
    },
    {
      "gen": 223,
      "best_raw": -1.0,
      "best_fitness": [
        -1,
        -1,
        -1.0,
        -1.0,
        -1.0,
        -1.0
      ],
      "mean_raw_elite": -1.0,
      "elapsed_s": 4.226172685623169,
      "champ_raw": 19.29550679320724
    },
    {
      "gen": 224,
      "best_raw": -1.0,
      "best_fitness": [
        -1,
        -1,
        -1.0,
        -1.0,
        -1.0,
        -1.0
      ],
      "mean_raw_elite": -1.0,
      "elapsed_s": 4.3354151248931885,
      "champ_raw": 19.29550679320724
    },
    {
      "gen": 225,
      "best_raw": -1.0,
      "best_fitness": [
        -1,
        -1,
        -1.0,
        -1.0,
        -1.0,
        -1.0
      ],
      "mean_raw_elite": -1.0,
      "elapsed_s": 4.296412944793701,
      "champ_raw": 19.29550679320724
    },
    {
      "gen": 226,
      "best_raw": -1.0,
      "best_fitness": [
        -1,
        -1,
        -1.0,
        -1.0,
        -1.0,
        -1.0
      ],
      "mean_raw_elite": -1.0,
      "elapsed_s": 4.275782585144043,
      "champ_raw": 19.29550679320724
    },
    {
      "gen": 227,
      "best_raw": -1.0,
      "best_fitness": [
        -1,
        -1,
        -1.0,
        -1.0,
        -1.0,
        -1.0
      ],
      "mean_raw_elite": -1.0,
      "elapsed_s": 4.6493306159973145,
      "champ_raw": 19.29550679320724
    },
    {
      "gen": 228,
      "best_raw": -1.0,
      "best_fitness": [
        -1,
        -1,
        -1.0,
        -1.0,
        -1.0,
        -1.0
      ],
      "mean_raw_elite": -1.0,
      "elapsed_s": 4.3670830726623535,
      "champ_raw": 19.29550679320724
    },
    {
      "gen": 229,
      "best_raw": -1.0,
      "best_fitness": [
        -1,
        -1,
        -1.0,
        -1.0,
        -1.0,
        -1.0
      ],
      "mean_raw_elite": -1.0,
      "elapsed_s": 4.230574131011963,
      "champ_raw": 19.29550679320724
    },
    {
      "gen": 230,
      "best_raw": -1.0,
      "best_fitness": [
        -1,
        -1,
        -1.0,
        -1.0,
        -1.0,
        -1.0
      ],
      "mean_raw_elite": -1.0,
      "elapsed_s": 4.309878587722778,
      "champ_raw": 19.29550679320724
    },
    {
      "gen": 231,
      "best_raw": -1.0,
      "best_fitness": [
        -1,
        -1,
        -1.0,
        -1.0,
        -1.0,
        -1.0
      ],
      "mean_raw_elite": -1.0,
      "elapsed_s": 4.238656282424927,
      "champ_raw": 19.29550679320724
    },
    {
      "gen": 232,
      "best_raw": -1.0,
      "best_fitness": [
        -1,
        -1,
        -1.0,
        -1.0,
        -1.0,
        -1.0
      ],
      "mean_raw_elite": -1.0,
      "elapsed_s": 4.289602041244507,
      "champ_raw": 19.29550679320724
    },
    {
      "gen": 233,
      "best_raw": -1.0,
      "best_fitness": [
        -1,
        -1,
        -1.0,
        -1.0,
        -1.0,
        -1.0
      ],
      "mean_raw_elite": -1.0,
      "elapsed_s": 4.344700336456299,
      "champ_raw": 19.29550679320724
    },
    {
      "gen": 234,
      "best_raw": -1.0,
      "best_fitness": [
        -1,
        -1,
        -1.0,
        -1.0,
        -1.0,
        -1.0
      ],
      "mean_raw_elite": -1.0,
      "elapsed_s": 4.497593879699707,
      "champ_raw": 19.29550679320724
    },
    {
      "gen": 235,
      "best_raw": -1.0,
      "best_fitness": [
        -1,
        -1,
        -1.0,
        -1.0,
        -1.0,
        -1.0
      ],
      "mean_raw_elite": -1.0,
      "elapsed_s": 4.321616172790527,
      "champ_raw": 19.29550679320724
    },
    {
      "gen": 236,
      "best_raw": -1.0,
      "best_fitness": [
        -1,
        -1,
        -1.0,
        -1.0,
        -1.0,
        -1.0
      ],
      "mean_raw_elite": -1.0,
      "elapsed_s": 4.249679327011108,
      "champ_raw": 19.29550679320724
    },
    {
      "gen": 237,
      "best_raw": -1.0,
      "best_fitness": [
        -1,
        -1,
        -1.0,
        -1.0,
        -1.0,
        -1.0
      ],
      "mean_raw_elite": -1.0,
      "elapsed_s": 4.308570384979248,
      "champ_raw": 19.29550679320724
    },
    {
      "gen": 238,
      "best_raw": -1.0,
      "best_fitness": [
        -1,
        -1,
        -1.0,
        -1.0,
        -1.0,
        -1.0
      ],
      "mean_raw_elite": -1.0,
      "elapsed_s": 4.288853883743286,
      "champ_raw": 19.29550679320724
    },
    {
      "gen": 239,
      "best_raw": -1.0,
      "best_fitness": [
        -1,
        -1,
        -1.0,
        -1.0,
        -1.0,
        -1.0
      ],
      "mean_raw_elite": -1.0,
      "elapsed_s": 4.2234203815460205,
      "champ_raw": 19.29550679320724
    },
    {
      "gen": 240,
      "best_raw": -1.0,
      "best_fitness": [
        -1,
        -1,
        -1.0,
        -1.0,
        -1.0,
        -1.0
      ],
      "mean_raw_elite": -1.0,
      "elapsed_s": 4.234946250915527,
      "champ_raw": 19.29550679320724
    },
    {
      "gen": 241,
      "best_raw": -1.0,
      "best_fitness": [
        -1,
        -1,
        -1.0,
        -1.0,
        -1.0,
        -1.0
      ],
      "mean_raw_elite": -1.0,
      "elapsed_s": 4.341250658035278,
      "champ_raw": 19.29550679320724
    },
    {
      "gen": 242,
      "best_raw": -1.0,
      "best_fitness": [
        -1,
        -1,
        -1.0,
        -1.0,
        -1.0,
        -1.0
      ],
      "mean_raw_elite": -1.0,
      "elapsed_s": 4.169472694396973,
      "champ_raw": 19.29550679320724
    },
    {
      "gen": 243,
      "best_raw": -1.0,
      "best_fitness": [
        -1,
        -1,
        -1.0,
        -1.0,
        -1.0,
        -1.0
      ],
      "mean_raw_elite": -1.0,
      "elapsed_s": 4.245007514953613,
      "champ_raw": 19.29550679320724
    },
    {
      "gen": 244,
      "best_raw": -1.0,
      "best_fitness": [
        -1,
        -1,
        -1.0,
        -1.0,
        -1.0,
        -1.0
      ],
      "mean_raw_elite": -1.0,
      "elapsed_s": 4.271072626113892,
      "champ_raw": 19.29550679320724
    },
    {
      "gen": 245,
      "best_raw": -1.0,
      "best_fitness": [
        -1,
        -1,
        -1.0,
        -1.0,
        -1.0,
        -1.0
      ],
      "mean_raw_elite": -1.0,
      "elapsed_s": 4.34382963180542,
      "champ_raw": 19.29550679320724
    },
    {
      "gen": 246,
      "best_raw": -1.0,
      "best_fitness": [
        -1,
        -1,
        -1.0,
        -1.0,
        -1.0,
        -1.0
      ],
      "mean_raw_elite": -1.0,
      "elapsed_s": 4.296848297119141,
      "champ_raw": 19.29550679320724
    },
    {
      "gen": 247,
      "best_raw": -1.0,
      "best_fitness": [
        -1,
        -1,
        -1.0,
        -1.0,
        -1.0,
        -1.0
      ],
      "mean_raw_elite": -1.0,
      "elapsed_s": 4.253389120101929,
      "champ_raw": 19.29550679320724
    },
    {
      "gen": 248,
      "best_raw": -1.0,
      "best_fitness": [
        -1,
        -1,
        -1.0,
        -1.0,
        -1.0,
        -1.0
      ],
      "mean_raw_elite": -1.0,
      "elapsed_s": 4.326697111129761,
      "champ_raw": 19.29550679320724
    }
  ],
  "best": {
    "raw_score_100": 19.29550679320724,
    "theta": {
      "quiet_ym_hot": 0.8682255005676511,
      "quiet_vy_hot": 2.289412944901186,
      "quiet_ym_mod": 0.5502061838909239,
      "quiet_mod_dt": 0.07840490107868801,
      "race_ym_arm": 0.7268679106530013,
      "race_meet_back": 0.4976760038440201,
      "race_far_y": 0.26470603431423484,
      "race_dxy_lo": 0.06,
      "race_dxy_hi": 0.6586976289052761,
      "race_far_off": 0.040574465569495066,
      "race_mix": 49.70690182639539,
      "race_ty_far": 0.8044785837121229,
      "race_ty_vy": 0.7746109021729634,
      "race_ty_g": 0.4184377003922424,
      "race_sep": 0.4126039250054476,
      "race_bvz_max": 1.6648288735952224,
      "lag_chase_x": 0.22,
      "lag_chase_z": 0.1,
      "lag_dz_lo": 0.02,
      "lag_dxy_hi_cap": 0.34,
      "lag_up": 0.1,
      "lag_mix_boost": 8.0,
      "lag_arm_bx": 1.7,
      "lag_behind_eps": 0.05,
      "hot_far_soft": -0.12,
      "coast_after_contact": 0.4448535548863865,
      "early_tip_mix": 30.196234515766545,
      "early_tip_ty_far": 0.7697951686973045,
      "early_tip_ty_vy": 0.3249543647096565,
      "band2_tend_base": 0.8883223333005917,
      "band2_tend_span": 0.01285213016983205,
      "b1_ym": 0.9046155522646308,
      "b1_vy_max": 1.9502608072193333,
      "b1_by_min": 0.12611369999187508,
      "b1_t0": 0.5006234287517138,
      "b1_t1": 0.5796200187311379,
      "cold_ym_lo": 1.2,
      "cold_ym_hi": 1.25,
      "cold_ym_mid": 0.771077151091583,
      "cold_ym_mid_hi": 1.05,
      "cold_ym": 0.771077151091583,
      "cold_vy_max": 1.170512444468784,
      "cold_by_abs_max": 0.8765191862422826,
      "cold_t0": 0.5398475096810477,
      "cold_t1": 0.7124173605689329,
      "cold_tend": 0.9113292570196927,
      "cold_inside": 0.1742851454580974,
      "launch1_tx": -0.1,
      "launch1_ty": 0.20668423533793084,
      "launch2_scale": 1.0,
      "launch2_tx": 0.004337874157701538,
      "launch2_ty": 0.05,
      "race_lim_span": 0.4,
      "dive_vz_kp": 5.0,
      "dive_vz_kd": 1.3,
      "dive_vz_max_down": -6.2
    },
    "path": null,
    "fitness": [
      21,
      6,
      2.0,
      0.5714285714285714,
      0.0,
      19.29550679320724
    ]
  },
  "champ_raw": 19.29550679320724,
  "final_mean": [
    0.8682255005676511,
    2.289412944901186,
    0.5502061838909239,
    0.07840490107868801,
    0.7268679106530013,
    0.4976760038440201,
    0.26470603431423484,
    0.06,
    0.6586976289052761,
    0.040574465569495066,
    49.70690182639539,
    0.8044785837121229,
    0.7746109021729634,
    0.4184377003922424,
    0.4126039250054476,
    1.6648288735952224,
    0.4448535548863865,
    30.196234515766545,
    0.7697951686973045,
    0.3249543647096565,
    0.8883223333005917,
    0.01285213016983205,
    0.9046155522646308,
    1.9502608072193333,
    0.12611369999187508,
    0.5006234287517138,
    0.5796200187311379,
    1.2,
    1.25,
    0.771077151091583,
    1.05,
    1.170512444468784,
    0.8765191862422826,
    0.5398475096810477,
    0.7124173605689329,
    0.9113292570196927,
    0.1742851454580974,
    -0.1,
    0.20668423533793084,
    1.0,
    0.004337874157701538,
    0.05,
    0.4,
    5.0,
    1.3,
    -6.2
  ],
  "final_std": [
    0.092,
    0.2875,
    0.092,
    0.046,
    0.11499999999999999,
    0.092,
    0.092,
    0.06899999999999999,
    0.092,
    0.046,
    6.8999999999999995,
    0.22999999999999998,
    0.1725,
    0.13799999999999998,
    0.092,
    0.22999999999999998,
    0.092,
    5.75,
    0.22999999999999998,
    0.13799999999999998,
    0.046,
    0.046,
    0.06899999999999999,
    0.22999999999999998,
    0.06899999999999999,
    0.023,
    0.023,
    0.046,
    0.046,
    0.06899999999999999,
    0.057499999999999996,
    0.1725,
    0.092,
    0.046,
    0.057499999999999996,
    0.057499999999999996,
    0.057499999999999996,
    0.057499999999999996,
    0.092,
    0.13799999999999998,
    0.046,
    0.06899999999999999,
    0.2875,
    1.15,
    0.345,
    0.9199999999999999
  ],
  "next_gen": 249
}